olab_open_api/__init__.py
olab_open_api/api_client.py
olab_open_api/api_response.py
olab_open_api/configuration.py
olab_open_api/exceptions.py
olab_open_api/py.typed
olab_open_api/rest.py
olab_open_api/api/__init__.py
olab_open_api/api/open_api_api.py
olab_open_api/api/user_api.py
olab_open_api/models/__init__.py
olab_open_api/models/models_topic_status.py
olab_open_api/models/openapi_balance_resp_open_api.py
olab_open_api/models/openapi_cancel_order_request_open_api.py
olab_open_api/models/openapi_cancel_order_resp_open_api.py
olab_open_api/models/openapi_child_market_data_open_api.py
olab_open_api/models/openapi_fee_rates_resp_open_api.py
olab_open_api/models/openapi_latest_price_resp_open_api.py
olab_open_api/models/openapi_market_categorical_market_id_get200_response.py
olab_open_api/models/openapi_market_data_open_api.py
olab_open_api/models/openapi_market_detail_resp_open_api.py
olab_open_api/models/openapi_market_get200_response.py
olab_open_api/models/openapi_market_list_resp_open_api.py
olab_open_api/models/openapi_order_cancel_post200_response.py
olab_open_api/models/openapi_order_data_open_api.py
olab_open_api/models/openapi_order_detail_resp_open_api.py
olab_open_api/models/openapi_order_get200_response.py
olab_open_api/models/openapi_order_list_resp_open_api.py
olab_open_api/models/openapi_order_order_id_get200_response.py
olab_open_api/models/openapi_order_post200_response.py
olab_open_api/models/openapi_orderbook_level.py
olab_open_api/models/openapi_orderbook_resp_open_api.py
olab_open_api/models/openapi_position_data_open_api.py
olab_open_api/models/openapi_positions_get200_response.py
olab_open_api/models/openapi_positions_resp_open_api.py
olab_open_api/models/openapi_price_history_resp_open_api.py
olab_open_api/models/openapi_price_point.py
olab_open_api/models/openapi_quote_token_balance.py
olab_open_api/models/openapi_quote_token_data_open_api.py
olab_open_api/models/openapi_quote_token_get200_response.py
olab_open_api-0.2.0.dist-info/METADATA
olab_open_api-0.2.0.dist-info/WHEEL
olab_open_api-0.2.0.dist-info/top_level.txt
olab_open_api-0.2.0.dist-info/RECORD
