Metadata-Version: 2.4
Name: olab_open_api
Version: 0.2.0
Summary: Prediction Market OpenAPI
Home-page: 
Author: API Support
Author-email: API Support <support@polymarket.com>
License-Expression: MIT
Project-URL: Repository, https://github.com/GIT_USER_ID/GIT_REPO_ID
Keywords: OpenAPI,OpenAPI-Generator,Prediction Market OpenAPI
Requires-Python: >=3.9
Requires-Dist: urllib3<3.0.0,>=2.1.0
Requires-Dist: python-dateutil>=2.8.2
Requires-Dist: pydantic>=2
Requires-Dist: typing-extensions>=4.7.1
Dynamic: author
